rinoh_typeface_texgyrecursor/GUST-FONT-LICENSE.txt
rinoh_typeface_texgyrecursor/README-TeX-Gyre-Cursor.txt
rinoh_typeface_texgyrecursor/__init__.py
rinoh_typeface_texgyrecursor/texgyrecursor-bold.otf
rinoh_typeface_texgyrecursor/texgyrecursor-bolditalic.otf
rinoh_typeface_texgyrecursor/texgyrecursor-italic.otf
rinoh_typeface_texgyrecursor/texgyrecursor-regular.otf
rinoh_typeface_texgyrecursor-0.1.1.dist-info/DESCRIPTION.rst
rinoh_typeface_texgyrecursor-0.1.1.dist-info/METADATA
rinoh_typeface_texgyrecursor-0.1.1.dist-info/RECORD
rinoh_typeface_texgyrecursor-0.1.1.dist-info/WHEEL
rinoh_typeface_texgyrecursor-0.1.1.dist-info/entry_points.txt
rinoh_typeface_texgyrecursor-0.1.1.dist-info/metadata.json
rinoh_typeface_texgyrecursor-0.1.1.dist-info/top_level.txt
